open_biopipeline/__init__.py
open_biopipeline/blast.py
open_biopipeline/kegg.py
open_biopipeline/proteinatlas.py
open_biopipeline/uniprot.py
open_biopipeline/webscrape.py
open_biopipeline/util/__init__.py
open_biopipeline/util/convert_to_fasta.py
open_biopipeline/util/xml_parser.py
open_biopipeline-0.0.4.dist-info/LICENSE
open_biopipeline-0.0.4.dist-info/METADATA
open_biopipeline-0.0.4.dist-info/WHEEL
open_biopipeline-0.0.4.dist-info/top_level.txt
open_biopipeline-0.0.4.dist-info/RECORD
