Metadata-Version: 2.1
Name: open-biopipeline
Version: 0.0.4
Summary: Welcome to Open Biopipeline, an open source gene exploration tool!
Home-page: https://github.com/gitUmaru/Open-Biopipeline
Author: Muhammad Umar Ali
Author-email: umaruali@student.ubc.ca
License: UNKNOWN
Platform: UNKNOWN
Classifier: Programming Language :: Python :: 3
Classifier: License :: OSI Approved :: MIT License
Classifier: Operating System :: OS Independent
Requires-Dist: biopython
Requires-Dist: uniprot
Requires-Dist: requests
Requires-Dist: matplotlib
Requires-Dist: beautifulsoup4
